LICENSE
README.md
setup.py
orbitkitabcdefg/__init__.py
orbitkitabcdefg.egg-info/PKG-INFO
orbitkitabcdefg.egg-info/SOURCES.txt
orbitkitabcdefg.egg-info/dependency_links.txt
orbitkitabcdefg.egg-info/requires.txt
orbitkitabcdefg.egg-info/top_level.txt