Metadata-Version: 2.1
Name: orbitkitabcdefg
Version: 0.0.8
Summary: This project is only for Orbit Tech internal use.
Home-page: https://github.com/clown-0726/orbitkit
Author: Lilu Cao
Author-email: lilu.cao@qq.com
Maintainer: Lilu Cao
Maintainer-email: lilu.cao@qq.com
License: MIT License
Platform: all
Classifier: Operating System :: OS Independent
Classifier: Intended Audience :: Developers
Classifier: License :: OSI Approved :: BSD License
Classifier: Programming Language :: Python
Classifier: Programming Language :: Python :: Implementation
Classifier: Programming Language :: Python :: 3
Classifier: Programming Language :: Python :: 3.4
Classifier: Programming Language :: Python :: 3.5
Classifier: Programming Language :: Python :: 3.6
Classifier: Programming Language :: Python :: 3.7
Classifier: Topic :: Software Development :: Libraries
License-File: LICENSE
